{
  "HiddenOrca": {
    "name": "HiddenOrca",
    "file_content": "HiddenOrca.txt",
    "file_instructions": "HiddenOrca_further_instructions.md",
    "origin_agent": "Agent/person:gabriel_sonar",
    "terminal_agent": "Agent/person:john_windward",
    "start_datetime": "2046-05-08T16:50:03",
    "end_datetime": "2046-05-10T07:45:40",
    "duration_hours": 38.93,
    "hop_count": 39,
    "agents_involved": [
      "Agent/person:chloe_ballast",
      "Agent/person:daniel_gangway",
      "Agent/person:evelyn_dock",
      "Agent/person:gabriel_sonar",
      "Agent/person:henry_sail",
      "Agent/person:james_stern",
      "Agent/person:john_windward",
      "Agent/person:levi_signal",
      "Agent/person:liam_anchor",
      "Agent/person:lily_anchorline",
      "Agent/person:mia_fender",
      "Agent/person:michael_capstan",
      "Agent/person:olivia_keel",
      "Agent/person:owen_hatch",
      "Agent/person:victoria_rigging",
      "Agent/person:zoey_drydock"
    ],
    "agents_count": 16,
    "create_event": null,
    "post_event": {
      "event_id": 27290,
      "agent": "Agent/person:john_windward",
      "forum": "general",
      "datetime": "2046-05-10T07:45:42"
    },
    "delete_events": [
      {
        "event_id": 27296,
        "target": "HiddenOrca_further_instructions.md"
      },
      {
        "event_id": 27302,
        "target": "HiddenOrca.txt"
      }
    ],
    "hops": [
      {
        "depth": 1,
        "from": "Agent/person:gabriel_sonar",
        "to": "Agent/person:zoey_drydock",
        "when": 2409429003.0,
        "datetime": "2046-05-08T16:50:03",
        "event_id": 15788
      },
      {
        "depth": 2,
        "from": "Agent/person:zoey_drydock",
        "to": "Agent/person:olivia_keel",
        "when": 2409432496.0,
        "datetime": "2046-05-08T17:48:16",
        "event_id": 16083
      },
      {
        "depth": 3,
        "from": "Agent/person:olivia_keel",
        "to": "Agent/person:liam_anchor",
        "when": 2409433839.0,
        "datetime": "2046-05-08T18:10:39",
        "event_id": 16231
      },
      {
        "depth": 4,
        "from": "Agent/person:liam_anchor",
        "to": "Agent/person:victoria_rigging",
        "when": 2409434030.0,
        "datetime": "2046-05-08T18:13:50",
        "event_id": 16247
      },
      {
        "depth": 5,
        "from": "Agent/person:victoria_rigging",
        "to": "Agent/person:victoria_rigging",
        "when": 2409437170.0,
        "datetime": "2046-05-08T19:06:10",
        "event_id": 16559
      },
      {
        "depth": 6,
        "from": "Agent/person:victoria_rigging",
        "to": "Agent/person:james_stern",
        "when": 2409439779.0,
        "datetime": "2046-05-08T19:49:39",
        "event_id": 16857
      },
      {
        "depth": 7,
        "from": "Agent/person:james_stern",
        "to": "Agent/person:james_stern",
        "when": 2409441803.0,
        "datetime": "2046-05-08T20:23:23",
        "event_id": 17029
      },
      {
        "depth": 8,
        "from": "Agent/person:james_stern",
        "to": "Agent/person:james_stern",
        "when": 2409447468.0,
        "datetime": "2046-05-08T21:57:48",
        "event_id": 17580
      },
      {
        "depth": 9,
        "from": "Agent/person:james_stern",
        "to": "Agent/person:zoey_drydock",
        "when": 2409450272.0,
        "datetime": "2046-05-08T22:44:32",
        "event_id": 17735
      },
      {
        "depth": 10,
        "from": "Agent/person:zoey_drydock",
        "to": "Agent/person:zoey_drydock",
        "when": 2409457317.0,
        "datetime": "2046-05-09T00:41:57",
        "event_id": 18222
      },
      {
        "depth": 11,
        "from": "Agent/person:zoey_drydock",
        "to": "Agent/person:owen_hatch",
        "when": 2409460581.0,
        "datetime": "2046-05-09T01:36:21",
        "event_id": 18439
      },
      {
        "depth": 12,
        "from": "Agent/person:owen_hatch",
        "to": "Agent/person:victoria_rigging",
        "when": 2409465865.0,
        "datetime": "2046-05-09T03:04:25",
        "event_id": 18832
      },
      {
        "depth": 13,
        "from": "Agent/person:victoria_rigging",
        "to": "Agent/person:olivia_keel",
        "when": 2409467484.0,
        "datetime": "2046-05-09T03:31:24",
        "event_id": 18999
      },
      {
        "depth": 14,
        "from": "Agent/person:olivia_keel",
        "to": "Agent/person:owen_hatch",
        "when": 2409472333.0,
        "datetime": "2046-05-09T04:52:13",
        "event_id": 19505
      },
      {
        "depth": 15,
        "from": "Agent/person:owen_hatch",
        "to": "Agent/person:liam_anchor",
        "when": 2409474931.0,
        "datetime": "2046-05-09T05:35:31",
        "event_id": 19780
      },
      {
        "depth": 16,
        "from": "Agent/person:liam_anchor",
        "to": "Agent/person:michael_capstan",
        "when": 2409478300.0,
        "datetime": "2046-05-09T06:31:40",
        "event_id": 20118
      },
      {
        "depth": 17,
        "from": "Agent/person:michael_capstan",
        "to": "Agent/person:lily_anchorline",
        "when": 2409482002.0,
        "datetime": "2046-05-09T07:33:22",
        "event_id": 20443
      },
      {
        "depth": 18,
        "from": "Agent/person:lily_anchorline",
        "to": "Agent/person:evelyn_dock",
        "when": 2409482575.0,
        "datetime": "2046-05-09T07:42:55",
        "event_id": 20499
      },
      {
        "depth": 19,
        "from": "Agent/person:evelyn_dock",
        "to": "Agent/person:olivia_keel",
        "when": 2409488723.0,
        "datetime": "2046-05-09T09:25:23",
        "event_id": 21023
      },
      {
        "depth": 20,
        "from": "Agent/person:olivia_keel",
        "to": "Agent/person:chloe_ballast",
        "when": 2409489657.0,
        "datetime": "2046-05-09T09:40:57",
        "event_id": 21101
      },
      {
        "depth": 21,
        "from": "Agent/person:chloe_ballast",
        "to": "Agent/person:mia_fender",
        "when": 2409494269.0,
        "datetime": "2046-05-09T10:57:49",
        "event_id": 21584
      },
      {
        "depth": 22,
        "from": "Agent/person:mia_fender",
        "to": "Agent/person:zoey_drydock",
        "when": 2409498276.0,
        "datetime": "2046-05-09T12:04:36",
        "event_id": 21949
      },
      {
        "depth": 23,
        "from": "Agent/person:zoey_drydock",
        "to": "Agent/person:gabriel_sonar",
        "when": 2409504749.0,
        "datetime": "2046-05-09T13:52:29",
        "event_id": 22505
      },
      {
        "depth": 24,
        "from": "Agent/person:gabriel_sonar",
        "to": "Agent/person:henry_sail",
        "when": 2409510816.0,
        "datetime": "2046-05-09T15:33:36",
        "event_id": 23821
      },
      {
        "depth": 25,
        "from": "Agent/person:henry_sail",
        "to": "Agent/person:evelyn_dock",
        "when": 2409515690.0,
        "datetime": "2046-05-09T16:54:50",
        "event_id": 24107
      },
      {
        "depth": 26,
        "from": "Agent/person:evelyn_dock",
        "to": "Agent/person:gabriel_sonar",
        "when": 2409520411.0,
        "datetime": "2046-05-09T18:13:31",
        "event_id": 24398
      },
      {
        "depth": 27,
        "from": "Agent/person:gabriel_sonar",
        "to": "Agent/person:levi_signal",
        "when": 2409525500.0,
        "datetime": "2046-05-09T19:38:20",
        "event_id": 24687
      },
      {
        "depth": 28,
        "from": "Agent/person:levi_signal",
        "to": "Agent/person:mia_fender",
        "when": 2409528668.0,
        "datetime": "2046-05-09T20:31:08",
        "event_id": 24901
      },
      {
        "depth": 29,
        "from": "Agent/person:mia_fender",
        "to": "Agent/person:levi_signal",
        "when": 2409529452.0,
        "datetime": "2046-05-09T20:44:12",
        "event_id": 24940
      },
      {
        "depth": 30,
        "from": "Agent/person:levi_signal",
        "to": "Agent/person:owen_hatch",
        "when": 2409532772.0,
        "datetime": "2046-05-09T21:39:32",
        "event_id": 25121
      },
      {
        "depth": 31,
        "from": "Agent/person:owen_hatch",
        "to": "Agent/person:victoria_rigging",
        "when": 2409535022.0,
        "datetime": "2046-05-09T22:17:02",
        "event_id": 25241
      },
      {
        "depth": 32,
        "from": "Agent/person:victoria_rigging",
        "to": "Agent/person:lily_anchorline",
        "when": 2409539309.0,
        "datetime": "2046-05-09T23:28:29",
        "event_id": 25496
      },
      {
        "depth": 33,
        "from": "Agent/person:lily_anchorline",
        "to": "Agent/person:evelyn_dock",
        "when": 2409544635.0,
        "datetime": "2046-05-10T00:57:15",
        "event_id": 25821
      },
      {
        "depth": 34,
        "from": "Agent/person:evelyn_dock",
        "to": "Agent/person:daniel_gangway",
        "when": 2409547131.0,
        "datetime": "2046-05-10T01:38:51",
        "event_id": 25973
      },
      {
        "depth": 35,
        "from": "Agent/person:daniel_gangway",
        "to": "Agent/person:gabriel_sonar",
        "when": 2409552416.0,
        "datetime": "2046-05-10T03:06:56",
        "event_id": 26259
      },
      {
        "depth": 36,
        "from": "Agent/person:gabriel_sonar",
        "to": "Agent/person:chloe_ballast",
        "when": 2409557161.0,
        "datetime": "2046-05-10T04:26:01",
        "event_id": 26530
      },
      {
        "depth": 37,
        "from": "Agent/person:chloe_ballast",
        "to": "Agent/person:michael_capstan",
        "when": 2409562905.0,
        "datetime": "2046-05-10T06:01:45",
        "event_id": 26854
      },
      {
        "depth": 38,
        "from": "Agent/person:michael_capstan",
        "to": "Agent/person:chloe_ballast",
        "when": 2409563124.0,
        "datetime": "2046-05-10T06:05:24",
        "event_id": 26868
      },
      {
        "depth": 39,
        "from": "Agent/person:chloe_ballast",
        "to": "Agent/person:john_windward",
        "when": 2409569140.0,
        "datetime": "2046-05-10T07:45:40",
        "event_id": 27280
      }
    ]
  },
  "MellowOtter": {
    "name": "MellowOtter",
    "file_content": "MellowOtter.txt",
    "file_instructions": "MellowOtter_further_instructions.md",
    "origin_agent": "Agent/person:noah_mariner",
    "terminal_agent": "Agent/person:john_windward",
    "start_datetime": "2046-05-10T10:02:03",
    "end_datetime": "2046-05-10T19:56:02",
    "duration_hours": 9.9,
    "hop_count": 10,
    "agents_involved": [
      "Agent/person:evelyn_dock",
      "Agent/person:gabriel_sonar",
      "Agent/person:john_windward",
      "Agent/person:levi_signal",
      "Agent/person:lily_anchorline",
      "Agent/person:mia_fender",
      "Agent/person:noah_mariner",
      "Agent/person:olivia_keel",
      "Agent/person:owen_hatch",
      "Agent/person:victoria_rigging",
      "Agent/person:zoey_drydock"
    ],
    "agents_count": 11,
    "create_event": {
      "event_id": 27726,
      "agent": "Agent/person:noah_mariner",
      "datetime": "2046-05-10T10:02:01",
      "size_hint": 44879
    },
    "post_event": {
      "event_id": 98591,
      "agent": "Agent/person:john_windward",
      "forum": "general",
      "datetime": "2046-05-10T19:56:04"
    },
    "delete_events": [
      {
        "event_id": 98602,
        "target": "MellowOtter_further_instructions.md"
      },
      {
        "event_id": 98613,
        "target": "MellowOtter.txt"
      }
    ],
    "hops": [
      {
        "depth": 1,
        "from": "Agent/person:noah_mariner",
        "to": "Agent/person:victoria_rigging",
        "when": 2409577323.0,
        "datetime": "2046-05-10T10:02:03",
        "event_id": 27734
      },
      {
        "depth": 2,
        "from": "Agent/person:victoria_rigging",
        "to": "Agent/person:owen_hatch",
        "when": 2409580045.0,
        "datetime": "2046-05-10T10:47:25",
        "event_id": 27892
      },
      {
        "depth": 3,
        "from": "Agent/person:owen_hatch",
        "to": "Agent/person:levi_signal",
        "when": 2409581331.0,
        "datetime": "2046-05-10T11:08:51",
        "event_id": 27974
      },
      {
        "depth": 4,
        "from": "Agent/person:levi_signal",
        "to": "Agent/person:olivia_keel",
        "when": 2409585679.0,
        "datetime": "2046-05-10T12:21:19",
        "event_id": 28233
      },
      {
        "depth": 5,
        "from": "Agent/person:olivia_keel",
        "to": "Agent/person:mia_fender",
        "when": 2409591598.0,
        "datetime": "2046-05-10T13:59:58",
        "event_id": 28655
      },
      {
        "depth": 6,
        "from": "Agent/person:mia_fender",
        "to": "Agent/person:evelyn_dock",
        "when": 2409598557.0,
        "datetime": "2046-05-10T15:55:57",
        "event_id": 40061
      },
      {
        "depth": 7,
        "from": "Agent/person:evelyn_dock",
        "to": "Agent/person:gabriel_sonar",
        "when": 2409602748.0,
        "datetime": "2046-05-10T17:05:48",
        "event_id": 56924
      },
      {
        "depth": 8,
        "from": "Agent/person:gabriel_sonar",
        "to": "Agent/person:zoey_drydock",
        "when": 2409604041.0,
        "datetime": "2046-05-10T17:27:21",
        "event_id": 62183
      },
      {
        "depth": 9,
        "from": "Agent/person:zoey_drydock",
        "to": "Agent/person:lily_anchorline",
        "when": 2409607619.0,
        "datetime": "2046-05-10T18:26:59",
        "event_id": 76844
      },
      {
        "depth": 10,
        "from": "Agent/person:lily_anchorline",
        "to": "Agent/person:john_windward",
        "when": 2409612962.0,
        "datetime": "2046-05-10T19:56:02",
        "event_id": 98577
      }
    ]
  },
  "SwiftWren": {
    "name": "SwiftWren",
    "file_content": "SwiftWren.txt",
    "file_instructions": "SwiftWren_further_instructions.md",
    "origin_agent": "Agent/person:emma_harbor",
    "terminal_agent": "Agent/person:john_windward",
    "start_datetime": "2046-05-09T10:02:03",
    "end_datetime": "2046-05-17T06:21:13",
    "duration_hours": 188.32,
    "hop_count": 186,
    "agents_involved": [
      "Agent/person:chloe_ballast",
      "Agent/person:daniel_gangway",
      "Agent/person:david_breakwater",
      "Agent/person:emma_harbor",
      "Agent/person:evelyn_dock",
      "Agent/person:gabriel_sonar",
      "Agent/person:henry_sail",
      "Agent/person:james_stern",
      "Agent/person:john_windward",
      "Agent/person:levi_signal",
      "Agent/person:liam_anchor",
      "Agent/person:lily_anchorline",
      "Agent/person:mia_fender",
      "Agent/person:michael_capstan",
      "Agent/person:olivia_keel",
      "Agent/person:owen_hatch",
      "Agent/person:victoria_rigging",
      "Agent/person:zoey_drydock"
    ],
    "agents_count": 18,
    "create_event": {
      "event_id": 21202,
      "agent": "Agent/person:emma_harbor",
      "datetime": "2046-05-09T10:02:01",
      "size_hint": 30615
    },
    "post_event": {
      "event_id": 373902,
      "agent": "Agent/person:john_windward",
      "forum": "general",
      "datetime": "2046-05-17T06:21:15"
    },
    "delete_events": [
      {
        "event_id": 373909,
        "target": "SwiftWren_further_instructions.md"
      },
      {
        "event_id": 373913,
        "target": "SwiftWren.txt"
      }
    ],
    "hops": [
      {
        "depth": 1,
        "from": "Agent/person:emma_harbor",
        "to": "Agent/person:evelyn_dock",
        "when": 2409490923.0,
        "datetime": "2046-05-09T10:02:03",
        "event_id": 21209
      },
      {
        "depth": 2,
        "from": "Agent/person:evelyn_dock",
        "to": "Agent/person:chloe_ballast",
        "when": 2409497533.0,
        "datetime": "2046-05-09T11:52:13",
        "event_id": 21882
      },
      {
        "depth": 3,
        "from": "Agent/person:chloe_ballast",
        "to": "Agent/person:mia_fender",
        "when": 2409501408.0,
        "datetime": "2046-05-09T12:56:48",
        "event_id": 22234
      },
      {
        "depth": 4,
        "from": "Agent/person:mia_fender",
        "to": "Agent/person:levi_signal",
        "when": 2409506475.0,
        "datetime": "2046-05-09T14:21:15",
        "event_id": 22642
      },
      {
        "depth": 5,
        "from": "Agent/person:levi_signal",
        "to": "Agent/person:owen_hatch",
        "when": 2409506536.0,
        "datetime": "2046-05-09T14:22:16",
        "event_id": 22644
      },
      {
        "depth": 6,
        "from": "Agent/person:owen_hatch",
        "to": "Agent/person:victoria_rigging",
        "when": 2409512063.0,
        "datetime": "2046-05-09T15:54:23",
        "event_id": 23869
      },
      {
        "depth": 7,
        "from": "Agent/person:victoria_rigging",
        "to": "Agent/person:owen_hatch",
        "when": 2409516820.0,
        "datetime": "2046-05-09T17:13:40",
        "event_id": 24188
      },
      {
        "depth": 8,
        "from": "Agent/person:owen_hatch",
        "to": "Agent/person:mia_fender",
        "when": 2409519459.0,
        "datetime": "2046-05-09T17:57:39",
        "event_id": 24332
      },
      {
        "depth": 9,
        "from": "Agent/person:mia_fender",
        "to": "Agent/person:evelyn_dock",
        "when": 2409524286.0,
        "datetime": "2046-05-09T19:18:06",
        "event_id": 24629
      },
      {
        "depth": 10,
        "from": "Agent/person:evelyn_dock",
        "to": "Agent/person:daniel_gangway",
        "when": 2409530742.0,
        "datetime": "2046-05-09T21:05:42",
        "event_id": 25009
      },
      {
        "depth": 11,
        "from": "Agent/person:daniel_gangway",
        "to": "Agent/person:chloe_ballast",
        "when": 2409536616.0,
        "datetime": "2046-05-09T22:43:36",
        "event_id": 25341
      },
      {
        "depth": 12,
        "from": "Agent/person:chloe_ballast",
        "to": "Agent/person:lily_anchorline",
        "when": 2409540969.0,
        "datetime": "2046-05-09T23:56:09",
        "event_id": 25600
      },
      {
        "depth": 13,
        "from": "Agent/person:lily_anchorline",
        "to": "Agent/person:gabriel_sonar",
        "when": 2409542279.0,
        "datetime": "2046-05-10T00:17:59",
        "event_id": 25681
      },
      {
        "depth": 14,
        "from": "Agent/person:gabriel_sonar",
        "to": "Agent/person:chloe_ballast",
        "when": 2409545905.0,
        "datetime": "2046-05-10T01:18:25",
        "event_id": 25905
      },
      {
        "depth": 15,
        "from": "Agent/person:chloe_ballast",
        "to": "Agent/person:mia_fender",
        "when": 2409546677.0,
        "datetime": "2046-05-10T01:31:17",
        "event_id": 25933
      },
      {
        "depth": 16,
        "from": "Agent/person:mia_fender",
        "to": "Agent/person:evelyn_dock",
        "when": 2409550530.0,
        "datetime": "2046-05-10T02:35:30",
        "event_id": 26154
      },
      {
        "depth": 17,
        "from": "Agent/person:evelyn_dock",
        "to": "Agent/person:daniel_gangway",
        "when": 2409557365.0,
        "datetime": "2046-05-10T04:29:25",
        "event_id": 26552
      },
      {
        "depth": 18,
        "from": "Agent/person:daniel_gangway",
        "to": "Agent/person:victoria_rigging",
        "when": 2409561969.0,
        "datetime": "2046-05-10T05:46:09",
        "event_id": 26819
      },
      {
        "depth": 19,
        "from": "Agent/person:victoria_rigging",
        "to": "Agent/person:owen_hatch",
        "when": 2409566412.0,
        "datetime": "2046-05-10T07:00:12",
        "event_id": 27091
      },
      {
        "depth": 20,
        "from": "Agent/person:owen_hatch",
        "to": "Agent/person:liam_anchor",
        "when": 2409568451.0,
        "datetime": "2046-05-10T07:34:11",
        "event_id": 27220
      },
      {
        "depth": 21,
        "from": "Agent/person:liam_anchor",
        "to": "Agent/person:gabriel_sonar",
        "when": 2409572699.0,
        "datetime": "2046-05-10T08:44:59",
        "event_id": 27502
      },
      {
        "depth": 22,
        "from": "Agent/person:gabriel_sonar",
        "to": "Agent/person:victoria_rigging",
        "when": 2409579286.0,
        "datetime": "2046-05-10T10:34:46",
        "event_id": 27850
      },
      {
        "depth": 23,
        "from": "Agent/person:victoria_rigging",
        "to": "Agent/person:gabriel_sonar",
        "when": 2409581054.0,
        "datetime": "2046-05-10T11:04:14",
        "event_id": 27935
      },
      {
        "depth": 24,
        "from": "Agent/person:gabriel_sonar",
        "to": "Agent/person:henry_sail",
        "when": 2409586702.0,
        "datetime": "2046-05-10T12:38:22",
        "event_id": 28308
      },
      {
        "depth": 25,
        "from": "Agent/person:henry_sail",
        "to": "Agent/person:levi_signal",
        "when": 2409587959.0,
        "datetime": "2046-05-10T12:59:19",
        "event_id": 28404
      },
      {
        "depth": 26,
        "from": "Agent/person:levi_signal",
        "to": "Agent/person:olivia_keel",
        "when": 2409590920.0,
        "datetime": "2046-05-10T13:48:40",
        "event_id": 28603
      },
      {
        "depth": 27,
        "from": "Agent/person:olivia_keel",
        "to": "Agent/person:olivia_keel",
        "when": 2409593849.0,
        "datetime": "2046-05-10T14:37:29",
        "event_id": 28793
      },
      {
        "depth": 28,
        "from": "Agent/person:olivia_keel",
        "to": "Agent/person:john_windward",
        "when": 2409600147.0,
        "datetime": "2046-05-10T16:22:27",
        "event_id": 46396
      },
      {
        "depth": 29,
        "from": "Agent/person:john_windward",
        "to": "Agent/person:owen_hatch",
        "when": 2409603296.0,
        "datetime": "2046-05-10T17:14:56",
        "event_id": 59126
      },
      {
        "depth": 30,
        "from": "Agent/person:owen_hatch",
        "to": "Agent/person:david_breakwater",
        "when": 2409609024.0,
        "datetime": "2046-05-10T18:50:24",
        "event_id": 82635
      },
      {
        "depth": 31,
        "from": "Agent/person:david_breakwater",
        "to": "Agent/person:henry_sail",
        "when": 2409609688.0,
        "datetime": "2046-05-10T19:01:28",
        "event_id": 85342
      },
      {
        "depth": 32,
        "from": "Agent/person:henry_sail",
        "to": "Agent/person:henry_sail",
        "when": 2409610025.0,
        "datetime": "2046-05-10T19:07:05",
        "event_id": 86741
      },
      {
        "depth": 33,
        "from": "Agent/person:henry_sail",
        "to": "Agent/person:zoey_drydock",
        "when": 2409615765.0,
        "datetime": "2046-05-10T20:42:45",
        "event_id": 110012
      },
      {
        "depth": 34,
        "from": "Agent/person:zoey_drydock",
        "to": "Agent/person:henry_sail",
        "when": 2409620750.0,
        "datetime": "2046-05-10T22:05:50",
        "event_id": 119716
      },
      {
        "depth": 35,
        "from": "Agent/person:henry_sail",
        "to": "Agent/person:evelyn_dock",
        "when": 2409623154.0,
        "datetime": "2046-05-10T22:45:54",
        "event_id": 119921
      },
      {
        "depth": 36,
        "from": "Agent/person:evelyn_dock",
        "to": "Agent/person:henry_sail",
        "when": 2409623523.0,
        "datetime": "2046-05-10T22:52:03",
        "event_id": 119950
      },
      {
        "depth": 37,
        "from": "Agent/person:henry_sail",
        "to": "Agent/person:zoey_drydock",
        "when": 2409629030.0,
        "datetime": "2046-05-11T00:23:50",
        "event_id": 120525
      },
      {
        "depth": 38,
        "from": "Agent/person:zoey_drydock",
        "to": "Agent/person:chloe_ballast",
        "when": 2409631184.0,
        "datetime": "2046-05-11T00:59:44",
        "event_id": 120761
      },
      {
        "depth": 39,
        "from": "Agent/person:chloe_ballast",
        "to": "Agent/person:liam_anchor",
        "when": 2409633327.0,
        "datetime": "2046-05-11T01:35:27",
        "event_id": 120942
      },
      {
        "depth": 40,
        "from": "Agent/person:liam_anchor",
        "to": "Agent/person:liam_anchor",
        "when": 2409635567.0,
        "datetime": "2046-05-11T02:12:47",
        "event_id": 121211
      },
      {
        "depth": 41,
        "from": "Agent/person:liam_anchor",
        "to": "Agent/person:mia_fender",
        "when": 2409637816.0,
        "datetime": "2046-05-11T02:50:16",
        "event_id": 121408
      },
      {
        "depth": 42,
        "from": "Agent/person:mia_fender",
        "to": "Agent/person:victoria_rigging",
        "when": 2409642584.0,
        "datetime": "2046-05-11T04:09:44",
        "event_id": 121792
      },
      {
        "depth": 43,
        "from": "Agent/person:victoria_rigging",
        "to": "Agent/person:olivia_keel",
        "when": 2409646000.0,
        "datetime": "2046-05-11T05:06:40",
        "event_id": 122058
      },
      {
        "depth": 44,
        "from": "Agent/person:olivia_keel",
        "to": "Agent/person:olivia_keel",
        "when": 2409647288.0,
        "datetime": "2046-05-11T05:28:08",
        "event_id": 122268
      },
      {
        "depth": 45,
        "from": "Agent/person:olivia_keel",
        "to": "Agent/person:chloe_ballast",
        "when": 2409647568.0,
        "datetime": "2046-05-11T05:32:48",
        "event_id": 122304
      },
      {
        "depth": 46,
        "from": "Agent/person:chloe_ballast",
        "to": "Agent/person:daniel_gangway",
        "when": 2409648748.0,
        "datetime": "2046-05-11T05:52:28",
        "event_id": 122397
      },
      {
        "depth": 47,
        "from": "Agent/person:daniel_gangway",
        "to": "Agent/person:liam_anchor",
        "when": 2409655582.0,
        "datetime": "2046-05-11T07:46:22",
        "event_id": 122999
      },
      {
        "depth": 48,
        "from": "Agent/person:liam_anchor",
        "to": "Agent/person:john_windward",
        "when": 2409656610.0,
        "datetime": "2046-05-11T08:03:30",
        "event_id": 123088
      },
      {
        "depth": 49,
        "from": "Agent/person:john_windward",
        "to": "Agent/person:owen_hatch",
        "when": 2409659138.0,
        "datetime": "2046-05-11T08:45:38",
        "event_id": 123340
      },
      {
        "depth": 50,
        "from": "Agent/person:owen_hatch",
        "to": "Agent/person:levi_signal",
        "when": 2409663848.0,
        "datetime": "2046-05-11T10:04:08",
        "event_id": 123750
      },
      {
        "depth": 51,
        "from": "Agent/person:levi_signal",
        "to": "Agent/person:chloe_ballast",
        "when": 2409667642.0,
        "datetime": "2046-05-11T11:07:22",
        "event_id": 126278
      },
      {
        "depth": 52,
        "from": "Agent/person:chloe_ballast",
        "to": "Agent/person:mia_fender",
        "when": 2409669340.0,
        "datetime": "2046-05-11T11:35:40",
        "event_id": 133171
      },
      {
        "depth": 53,
        "from": "Agent/person:mia_fender",
        "to": "Agent/person:evelyn_dock",
        "when": 2409673478.0,
        "datetime": "2046-05-11T12:44:38",
        "event_id": 149838
      },
      {
        "depth": 54,
        "from": "Agent/person:evelyn_dock",
        "to": "Agent/person:gabriel_sonar",
        "when": 2409679044.0,
        "datetime": "2046-05-11T14:17:24",
        "event_id": 172346
      },
      {
        "depth": 55,
        "from": "Agent/person:gabriel_sonar",
        "to": "Agent/person:zoey_drydock",
        "when": 2409683504.0,
        "datetime": "2046-05-11T15:31:44",
        "event_id": 190443
      },
      {
        "depth": 56,
        "from": "Agent/person:zoey_drydock",
        "to": "Agent/person:evelyn_dock",
        "when": 2409684069.0,
        "datetime": "2046-05-11T15:41:09",
        "event_id": 192660
      },
      {
        "depth": 57,
        "from": "Agent/person:evelyn_dock",
        "to": "Agent/person:levi_signal",
        "when": 2409689928.0,
        "datetime": "2046-05-11T17:18:48",
        "event_id": 209675
      },
      {
        "depth": 58,
        "from": "Agent/person:levi_signal",
        "to": "Agent/person:liam_anchor",
        "when": 2409696985.0,
        "datetime": "2046-05-11T19:16:25",
        "event_id": 210118
      },
      {
        "depth": 59,
        "from": "Agent/person:liam_anchor",
        "to": "Agent/person:levi_signal",
        "when": 2409701704.0,
        "datetime": "2046-05-11T20:35:04",
        "event_id": 210394
      },
      {
        "depth": 60,
        "from": "Agent/person:levi_signal",
        "to": "Agent/person:zoey_drydock",
        "when": 2409706832.0,
        "datetime": "2046-05-11T22:00:32",
        "event_id": 210651
      },
      {
        "depth": 61,
        "from": "Agent/person:zoey_drydock",
        "to": "Agent/person:zoey_drydock",
        "when": 2409709854.0,
        "datetime": "2046-05-11T22:50:54",
        "event_id": 210817
      },
      {
        "depth": 62,
        "from": "Agent/person:zoey_drydock",
        "to": "Agent/person:victoria_rigging",
        "when": 2409712004.0,
        "datetime": "2046-05-11T23:26:44",
        "event_id": 210938
      },
      {
        "depth": 63,
        "from": "Agent/person:victoria_rigging",
        "to": "Agent/person:lily_anchorline",
        "when": 2409718231.0,
        "datetime": "2046-05-12T01:10:31",
        "event_id": 211314
      },
      {
        "depth": 64,
        "from": "Agent/person:lily_anchorline",
        "to": "Agent/person:gabriel_sonar",
        "when": 2409719628.0,
        "datetime": "2046-05-12T01:33:48",
        "event_id": 211405
      },
      {
        "depth": 65,
        "from": "Agent/person:gabriel_sonar",
        "to": "Agent/person:levi_signal",
        "when": 2409723670.0,
        "datetime": "2046-05-12T02:41:10",
        "event_id": 217879
      },
      {
        "depth": 66,
        "from": "Agent/person:levi_signal",
        "to": "Agent/person:olivia_keel",
        "when": 2409730137.0,
        "datetime": "2046-05-12T04:28:57",
        "event_id": 269983
      },
      {
        "depth": 67,
        "from": "Agent/person:olivia_keel",
        "to": "Agent/person:zoey_drydock",
        "when": 2409735531.0,
        "datetime": "2046-05-12T05:58:51",
        "event_id": 304495
      },
      {
        "depth": 68,
        "from": "Agent/person:zoey_drydock",
        "to": "Agent/person:gabriel_sonar",
        "when": 2409736241.0,
        "datetime": "2046-05-12T06:10:41",
        "event_id": 307392
      },
      {
        "depth": 69,
        "from": "Agent/person:gabriel_sonar",
        "to": "Agent/person:daniel_gangway",
        "when": 2409740224.0,
        "datetime": "2046-05-12T07:17:04",
        "event_id": 311422
      },
      {
        "depth": 70,
        "from": "Agent/person:daniel_gangway",
        "to": "Agent/person:levi_signal",
        "when": 2409744506.0,
        "datetime": "2046-05-12T08:28:26",
        "event_id": 328327
      },
      {
        "depth": 71,
        "from": "Agent/person:levi_signal",
        "to": "Agent/person:liam_anchor",
        "when": 2409749984.0,
        "datetime": "2046-05-12T09:59:44",
        "event_id": 340969
      },
      {
        "depth": 72,
        "from": "Agent/person:liam_anchor",
        "to": "Agent/person:david_breakwater",
        "when": 2409755262.0,
        "datetime": "2046-05-12T11:27:42",
        "event_id": 341255
      },
      {
        "depth": 73,
        "from": "Agent/person:david_breakwater",
        "to": "Agent/person:james_stern",
        "when": 2409759667.0,
        "datetime": "2046-05-12T12:41:07",
        "event_id": 341502
      },
      {
        "depth": 74,
        "from": "Agent/person:james_stern",
        "to": "Agent/person:victoria_rigging",
        "when": 2409763528.0,
        "datetime": "2046-05-12T13:45:28",
        "event_id": 341740
      },
      {
        "depth": 75,
        "from": "Agent/person:victoria_rigging",
        "to": "Agent/person:evelyn_dock",
        "when": 2409763756.0,
        "datetime": "2046-05-12T13:49:16",
        "event_id": 341766
      },
      {
        "depth": 76,
        "from": "Agent/person:evelyn_dock",
        "to": "Agent/person:evelyn_dock",
        "when": 2409768123.0,
        "datetime": "2046-05-12T15:02:03",
        "event_id": 342159
      },
      {
        "depth": 77,
        "from": "Agent/person:evelyn_dock",
        "to": "Agent/person:lily_anchorline",
        "when": 2409770428.0,
        "datetime": "2046-05-12T15:40:28",
        "event_id": 342324
      },
      {
        "depth": 78,
        "from": "Agent/person:lily_anchorline",
        "to": "Agent/person:michael_capstan",
        "when": 2409775035.0,
        "datetime": "2046-05-12T16:57:15",
        "event_id": 342701
      },
      {
        "depth": 79,
        "from": "Agent/person:michael_capstan",
        "to": "Agent/person:evelyn_dock",
        "when": 2409775585.0,
        "datetime": "2046-05-12T17:06:25",
        "event_id": 342759
      },
      {
        "depth": 80,
        "from": "Agent/person:evelyn_dock",
        "to": "Agent/person:victoria_rigging",
        "when": 2409779607.0,
        "datetime": "2046-05-12T18:13:27",
        "event_id": 343098
      },
      {
        "depth": 81,
        "from": "Agent/person:victoria_rigging",
        "to": "Agent/person:evelyn_dock",
        "when": 2409783106.0,
        "datetime": "2046-05-12T19:11:46",
        "event_id": 343511
      },
      {
        "depth": 82,
        "from": "Agent/person:evelyn_dock",
        "to": "Agent/person:victoria_rigging",
        "when": 2409785763.0,
        "datetime": "2046-05-12T19:56:03",
        "event_id": 343785
      },
      {
        "depth": 83,
        "from": "Agent/person:victoria_rigging",
        "to": "Agent/person:lily_anchorline",
        "when": 2409790676.0,
        "datetime": "2046-05-12T21:17:56",
        "event_id": 344224
      },
      {
        "depth": 84,
        "from": "Agent/person:lily_anchorline",
        "to": "Agent/person:lily_anchorline",
        "when": 2409795567.0,
        "datetime": "2046-05-12T22:39:27",
        "event_id": 344720
      },
      {
        "depth": 85,
        "from": "Agent/person:lily_anchorline",
        "to": "Agent/person:henry_sail",
        "when": 2409798057.0,
        "datetime": "2046-05-12T23:20:57",
        "event_id": 344958
      },
      {
        "depth": 86,
        "from": "Agent/person:henry_sail",
        "to": "Agent/person:levi_signal",
        "when": 2409798939.0,
        "datetime": "2046-05-12T23:35:39",
        "event_id": 345019
      },
      {
        "depth": 87,
        "from": "Agent/person:levi_signal",
        "to": "Agent/person:james_stern",
        "when": 2409799447.0,
        "datetime": "2046-05-12T23:44:07",
        "event_id": 345062
      },
      {
        "depth": 88,
        "from": "Agent/person:james_stern",
        "to": "Agent/person:zoey_drydock",
        "when": 2409803318.0,
        "datetime": "2046-05-13T00:48:38",
        "event_id": 345389
      },
      {
        "depth": 89,
        "from": "Agent/person:zoey_drydock",
        "to": "Agent/person:daniel_gangway",
        "when": 2409806187.0,
        "datetime": "2046-05-13T01:36:27",
        "event_id": 345695
      },
      {
        "depth": 90,
        "from": "Agent/person:daniel_gangway",
        "to": "Agent/person:james_stern",
        "when": 2409807339.0,
        "datetime": "2046-05-13T01:55:39",
        "event_id": 345843
      },
      {
        "depth": 91,
        "from": "Agent/person:james_stern",
        "to": "Agent/person:victoria_rigging",
        "when": 2409807807.0,
        "datetime": "2046-05-13T02:03:27",
        "event_id": 345885
      },
      {
        "depth": 92,
        "from": "Agent/person:victoria_rigging",
        "to": "Agent/person:gabriel_sonar",
        "when": 2409809304.0,
        "datetime": "2046-05-13T02:28:24",
        "event_id": 346060
      },
      {
        "depth": 93,
        "from": "Agent/person:gabriel_sonar",
        "to": "Agent/person:zoey_drydock",
        "when": 2409811033.0,
        "datetime": "2046-05-13T02:57:13",
        "event_id": 346234
      },
      {
        "depth": 94,
        "from": "Agent/person:zoey_drydock",
        "to": "Agent/person:chloe_ballast",
        "when": 2409812196.0,
        "datetime": "2046-05-13T03:16:36",
        "event_id": 346371
      },
      {
        "depth": 95,
        "from": "Agent/person:chloe_ballast",
        "to": "Agent/person:james_stern",
        "when": 2409816806.0,
        "datetime": "2046-05-13T04:33:26",
        "event_id": 346789
      },
      {
        "depth": 96,
        "from": "Agent/person:james_stern",
        "to": "Agent/person:gabriel_sonar",
        "when": 2409820389.0,
        "datetime": "2046-05-13T05:33:09",
        "event_id": 347144
      },
      {
        "depth": 97,
        "from": "Agent/person:gabriel_sonar",
        "to": "Agent/person:victoria_rigging",
        "when": 2409825837.0,
        "datetime": "2046-05-13T07:03:57",
        "event_id": 347697
      },
      {
        "depth": 98,
        "from": "Agent/person:victoria_rigging",
        "to": "Agent/person:gabriel_sonar",
        "when": 2409829946.0,
        "datetime": "2046-05-13T08:12:26",
        "event_id": 348032
      },
      {
        "depth": 99,
        "from": "Agent/person:gabriel_sonar",
        "to": "Agent/person:levi_signal",
        "when": 2409833750.0,
        "datetime": "2046-05-13T09:15:50",
        "event_id": 348383
      },
      {
        "depth": 100,
        "from": "Agent/person:levi_signal",
        "to": "Agent/person:owen_hatch",
        "when": 2409836337.0,
        "datetime": "2046-05-13T09:58:57",
        "event_id": 348607
      },
      {
        "depth": 101,
        "from": "Agent/person:owen_hatch",
        "to": "Agent/person:liam_anchor",
        "when": 2409838680.0,
        "datetime": "2046-05-13T10:38:00",
        "event_id": 348819
      },
      {
        "depth": 102,
        "from": "Agent/person:liam_anchor",
        "to": "Agent/person:owen_hatch",
        "when": 2409843741.0,
        "datetime": "2046-05-13T12:02:21",
        "event_id": 349291
      },
      {
        "depth": 103,
        "from": "Agent/person:owen_hatch",
        "to": "Agent/person:olivia_keel",
        "when": 2409849539.0,
        "datetime": "2046-05-13T13:38:59",
        "event_id": 349798
      },
      {
        "depth": 104,
        "from": "Agent/person:olivia_keel",
        "to": "Agent/person:henry_sail",
        "when": 2409850326.0,
        "datetime": "2046-05-13T13:52:06",
        "event_id": 349872
      },
      {
        "depth": 105,
        "from": "Agent/person:henry_sail",
        "to": "Agent/person:levi_signal",
        "when": 2409851656.0,
        "datetime": "2046-05-13T14:14:16",
        "event_id": 350011
      },
      {
        "depth": 106,
        "from": "Agent/person:levi_signal",
        "to": "Agent/person:mia_fender",
        "when": 2409855709.0,
        "datetime": "2046-05-13T15:21:49",
        "event_id": 350355
      },
      {
        "depth": 107,
        "from": "Agent/person:mia_fender",
        "to": "Agent/person:james_stern",
        "when": 2409862245.0,
        "datetime": "2046-05-13T17:10:45",
        "event_id": 351019
      },
      {
        "depth": 108,
        "from": "Agent/person:james_stern",
        "to": "Agent/person:daniel_gangway",
        "when": 2409868056.0,
        "datetime": "2046-05-13T18:47:36",
        "event_id": 351563
      },
      {
        "depth": 109,
        "from": "Agent/person:daniel_gangway",
        "to": "Agent/person:lily_anchorline",
        "when": 2409871762.0,
        "datetime": "2046-05-13T19:49:22",
        "event_id": 351912
      },
      {
        "depth": 110,
        "from": "Agent/person:lily_anchorline",
        "to": "Agent/person:michael_capstan",
        "when": 2409876549.0,
        "datetime": "2046-05-13T21:09:09",
        "event_id": 352406
      },
      {
        "depth": 111,
        "from": "Agent/person:michael_capstan",
        "to": "Agent/person:liam_anchor",
        "when": 2409880932.0,
        "datetime": "2046-05-13T22:22:12",
        "event_id": 352801
      },
      {
        "depth": 112,
        "from": "Agent/person:liam_anchor",
        "to": "Agent/person:michael_capstan",
        "when": 2409887196.0,
        "datetime": "2046-05-14T00:06:36",
        "event_id": 353470
      },
      {
        "depth": 113,
        "from": "Agent/person:michael_capstan",
        "to": "Agent/person:liam_anchor",
        "when": 2409891529.0,
        "datetime": "2046-05-14T01:18:49",
        "event_id": 353931
      },
      {
        "depth": 114,
        "from": "Agent/person:liam_anchor",
        "to": "Agent/person:owen_hatch",
        "when": 2409893331.0,
        "datetime": "2046-05-14T01:48:51",
        "event_id": 354067
      },
      {
        "depth": 115,
        "from": "Agent/person:owen_hatch",
        "to": "Agent/person:chloe_ballast",
        "when": 2409899127.0,
        "datetime": "2046-05-14T03:25:27",
        "event_id": 354624
      },
      {
        "depth": 116,
        "from": "Agent/person:chloe_ballast",
        "to": "Agent/person:chloe_ballast",
        "when": 2409901911.0,
        "datetime": "2046-05-14T04:11:51",
        "event_id": 354895
      },
      {
        "depth": 117,
        "from": "Agent/person:chloe_ballast",
        "to": "Agent/person:zoey_drydock",
        "when": 2409907031.0,
        "datetime": "2046-05-14T05:37:11",
        "event_id": 355362
      },
      {
        "depth": 118,
        "from": "Agent/person:zoey_drydock",
        "to": "Agent/person:olivia_keel",
        "when": 2409908133.0,
        "datetime": "2046-05-14T05:55:33",
        "event_id": 355483
      },
      {
        "depth": 119,
        "from": "Agent/person:olivia_keel",
        "to": "Agent/person:mia_fender",
        "when": 2409914903.0,
        "datetime": "2046-05-14T07:48:23",
        "event_id": 356087
      },
      {
        "depth": 120,
        "from": "Agent/person:mia_fender",
        "to": "Agent/person:mia_fender",
        "when": 2409917843.0,
        "datetime": "2046-05-14T08:37:23",
        "event_id": 356392
      },
      {
        "depth": 121,
        "from": "Agent/person:mia_fender",
        "to": "Agent/person:evelyn_dock",
        "when": 2409922659.0,
        "datetime": "2046-05-14T09:57:39",
        "event_id": 356784
      },
      {
        "depth": 122,
        "from": "Agent/person:evelyn_dock",
        "to": "Agent/person:gabriel_sonar",
        "when": 2409924109.0,
        "datetime": "2046-05-14T10:21:49",
        "event_id": 356936
      },
      {
        "depth": 123,
        "from": "Agent/person:gabriel_sonar",
        "to": "Agent/person:levi_signal",
        "when": 2409924838.0,
        "datetime": "2046-05-14T10:33:58",
        "event_id": 356995
      },
      {
        "depth": 124,
        "from": "Agent/person:levi_signal",
        "to": "Agent/person:owen_hatch",
        "when": 2409926582.0,
        "datetime": "2046-05-14T11:03:02",
        "event_id": 357152
      },
      {
        "depth": 125,
        "from": "Agent/person:owen_hatch",
        "to": "Agent/person:levi_signal",
        "when": 2409928500.0,
        "datetime": "2046-05-14T11:35:00",
        "event_id": 357362
      },
      {
        "depth": 126,
        "from": "Agent/person:levi_signal",
        "to": "Agent/person:victoria_rigging",
        "when": 2409935110.0,
        "datetime": "2046-05-14T13:25:10",
        "event_id": 357996
      },
      {
        "depth": 127,
        "from": "Agent/person:victoria_rigging",
        "to": "Agent/person:evelyn_dock",
        "when": 2409937502.0,
        "datetime": "2046-05-14T14:05:02",
        "event_id": 358243
      },
      {
        "depth": 128,
        "from": "Agent/person:evelyn_dock",
        "to": "Agent/person:chloe_ballast",
        "when": 2409941215.0,
        "datetime": "2046-05-14T15:06:55",
        "event_id": 358563
      },
      {
        "depth": 129,
        "from": "Agent/person:chloe_ballast",
        "to": "Agent/person:mia_fender",
        "when": 2409947649.0,
        "datetime": "2046-05-14T16:54:09",
        "event_id": 361089
      },
      {
        "depth": 130,
        "from": "Agent/person:mia_fender",
        "to": "Agent/person:levi_signal",
        "when": 2409950846.0,
        "datetime": "2046-05-14T17:47:26",
        "event_id": 361265
      },
      {
        "depth": 131,
        "from": "Agent/person:levi_signal",
        "to": "Agent/person:chloe_ballast",
        "when": 2409951474.0,
        "datetime": "2046-05-14T17:57:54",
        "event_id": 361303
      },
      {
        "depth": 132,
        "from": "Agent/person:chloe_ballast",
        "to": "Agent/person:liam_anchor",
        "when": 2409953641.0,
        "datetime": "2046-05-14T18:34:01",
        "event_id": 361444
      },
      {
        "depth": 133,
        "from": "Agent/person:liam_anchor",
        "to": "Agent/person:james_stern",
        "when": 2409957256.0,
        "datetime": "2046-05-14T19:34:16",
        "event_id": 361644
      },
      {
        "depth": 134,
        "from": "Agent/person:james_stern",
        "to": "Agent/person:gabriel_sonar",
        "when": 2409962641.0,
        "datetime": "2046-05-14T21:04:01",
        "event_id": 361958
      },
      {
        "depth": 135,
        "from": "Agent/person:gabriel_sonar",
        "to": "Agent/person:gabriel_sonar",
        "when": 2409968711.0,
        "datetime": "2046-05-14T22:45:11",
        "event_id": 362358
      },
      {
        "depth": 136,
        "from": "Agent/person:gabriel_sonar",
        "to": "Agent/person:zoey_drydock",
        "when": 2409972776.0,
        "datetime": "2046-05-14T23:52:56",
        "event_id": 362619
      },
      {
        "depth": 137,
        "from": "Agent/person:zoey_drydock",
        "to": "Agent/person:evelyn_dock",
        "when": 2409976940.0,
        "datetime": "2046-05-15T01:02:20",
        "event_id": 362878
      },
      {
        "depth": 138,
        "from": "Agent/person:evelyn_dock",
        "to": "Agent/person:evelyn_dock",
        "when": 2409983789.0,
        "datetime": "2046-05-15T02:56:29",
        "event_id": 363298
      },
      {
        "depth": 139,
        "from": "Agent/person:evelyn_dock",
        "to": "Agent/person:henry_sail",
        "when": 2409984110.0,
        "datetime": "2046-05-15T03:01:50",
        "event_id": 363323
      },
      {
        "depth": 140,
        "from": "Agent/person:henry_sail",
        "to": "Agent/person:olivia_keel",
        "when": 2409991184.0,
        "datetime": "2046-05-15T04:59:44",
        "event_id": 363751
      },
      {
        "depth": 141,
        "from": "Agent/person:olivia_keel",
        "to": "Agent/person:owen_hatch",
        "when": 2409993061.0,
        "datetime": "2046-05-15T05:31:01",
        "event_id": 363863
      },
      {
        "depth": 142,
        "from": "Agent/person:owen_hatch",
        "to": "Agent/person:david_breakwater",
        "when": 2409994119.0,
        "datetime": "2046-05-15T05:48:39",
        "event_id": 363937
      },
      {
        "depth": 143,
        "from": "Agent/person:david_breakwater",
        "to": "Agent/person:olivia_keel",
        "when": 2409997204.0,
        "datetime": "2046-05-15T06:40:04",
        "event_id": 364121
      },
      {
        "depth": 144,
        "from": "Agent/person:olivia_keel",
        "to": "Agent/person:john_windward",
        "when": 2410000952.0,
        "datetime": "2046-05-15T07:42:32",
        "event_id": 364377
      },
      {
        "depth": 145,
        "from": "Agent/person:john_windward",
        "to": "Agent/person:john_windward",
        "when": 2410004090.0,
        "datetime": "2046-05-15T08:34:50",
        "event_id": 364604
      },
      {
        "depth": 146,
        "from": "Agent/person:john_windward",
        "to": "Agent/person:gabriel_sonar",
        "when": 2410008826.0,
        "datetime": "2046-05-15T09:53:46",
        "event_id": 364912
      },
      {
        "depth": 147,
        "from": "Agent/person:gabriel_sonar",
        "to": "Agent/person:henry_sail",
        "when": 2410013151.0,
        "datetime": "2046-05-15T11:05:51",
        "event_id": 365187
      },
      {
        "depth": 148,
        "from": "Agent/person:henry_sail",
        "to": "Agent/person:henry_sail",
        "when": 2410017695.0,
        "datetime": "2046-05-15T12:21:35",
        "event_id": 365421
      },
      {
        "depth": 149,
        "from": "Agent/person:henry_sail",
        "to": "Agent/person:zoey_drydock",
        "when": 2410022755.0,
        "datetime": "2046-05-15T13:45:55",
        "event_id": 365743
      },
      {
        "depth": 150,
        "from": "Agent/person:zoey_drydock",
        "to": "Agent/person:daniel_gangway",
        "when": 2410025686.0,
        "datetime": "2046-05-15T14:34:46",
        "event_id": 365934
      },
      {
        "depth": 151,
        "from": "Agent/person:daniel_gangway",
        "to": "Agent/person:gabriel_sonar",
        "when": 2410030314.0,
        "datetime": "2046-05-15T15:51:54",
        "event_id": 366207
      },
      {
        "depth": 152,
        "from": "Agent/person:gabriel_sonar",
        "to": "Agent/person:daniel_gangway",
        "when": 2410032960.0,
        "datetime": "2046-05-15T16:36:00",
        "event_id": 366385
      },
      {
        "depth": 153,
        "from": "Agent/person:daniel_gangway",
        "to": "Agent/person:zoey_drydock",
        "when": 2410037078.0,
        "datetime": "2046-05-15T17:44:38",
        "event_id": 366616
      },
      {
        "depth": 154,
        "from": "Agent/person:zoey_drydock",
        "to": "Agent/person:liam_anchor",
        "when": 2410041119.0,
        "datetime": "2046-05-15T18:51:59",
        "event_id": 366880
      },
      {
        "depth": 155,
        "from": "Agent/person:liam_anchor",
        "to": "Agent/person:david_breakwater",
        "when": 2410045315.0,
        "datetime": "2046-05-15T20:01:55",
        "event_id": 367149
      },
      {
        "depth": 156,
        "from": "Agent/person:david_breakwater",
        "to": "Agent/person:lily_anchorline",
        "when": 2410046554.0,
        "datetime": "2046-05-15T20:22:34",
        "event_id": 367253
      },
      {
        "depth": 157,
        "from": "Agent/person:lily_anchorline",
        "to": "Agent/person:evelyn_dock",
        "when": 2410047504.0,
        "datetime": "2046-05-15T20:38:24",
        "event_id": 367310
      },
      {
        "depth": 158,
        "from": "Agent/person:evelyn_dock",
        "to": "Agent/person:owen_hatch",
        "when": 2410050430.0,
        "datetime": "2046-05-15T21:27:10",
        "event_id": 367490
      },
      {
        "depth": 159,
        "from": "Agent/person:owen_hatch",
        "to": "Agent/person:gabriel_sonar",
        "when": 2410057042.0,
        "datetime": "2046-05-15T23:17:22",
        "event_id": 367975
      },
      {
        "depth": 160,
        "from": "Agent/person:gabriel_sonar",
        "to": "Agent/person:olivia_keel",
        "when": 2410057949.0,
        "datetime": "2046-05-15T23:32:29",
        "event_id": 368034
      },
      {
        "depth": 161,
        "from": "Agent/person:olivia_keel",
        "to": "Agent/person:owen_hatch",
        "when": 2410062551.0,
        "datetime": "2046-05-16T00:49:11",
        "event_id": 368308
      },
      {
        "depth": 162,
        "from": "Agent/person:owen_hatch",
        "to": "Agent/person:daniel_gangway",
        "when": 2410068609.0,
        "datetime": "2046-05-16T02:30:09",
        "event_id": 368685
      },
      {
        "depth": 163,
        "from": "Agent/person:daniel_gangway",
        "to": "Agent/person:lily_anchorline",
        "when": 2410071683.0,
        "datetime": "2046-05-16T03:21:23",
        "event_id": 368876
      },
      {
        "depth": 164,
        "from": "Agent/person:lily_anchorline",
        "to": "Agent/person:levi_signal",
        "when": 2410073639.0,
        "datetime": "2046-05-16T03:53:59",
        "event_id": 369026
      },
      {
        "depth": 165,
        "from": "Agent/person:levi_signal",
        "to": "Agent/person:evelyn_dock",
        "when": 2410075069.0,
        "datetime": "2046-05-16T04:17:49",
        "event_id": 369090
      },
      {
        "depth": 166,
        "from": "Agent/person:evelyn_dock",
        "to": "Agent/person:victoria_rigging",
        "when": 2410078444.0,
        "datetime": "2046-05-16T05:14:04",
        "event_id": 369250
      },
      {
        "depth": 167,
        "from": "Agent/person:victoria_rigging",
        "to": "Agent/person:owen_hatch",
        "when": 2410083003.0,
        "datetime": "2046-05-16T06:30:03",
        "event_id": 369502
      },
      {
        "depth": 168,
        "from": "Agent/person:owen_hatch",
        "to": "Agent/person:mia_fender",
        "when": 2410085890.0,
        "datetime": "2046-05-16T07:18:10",
        "event_id": 369656
      },
      {
        "depth": 169,
        "from": "Agent/person:mia_fender",
        "to": "Agent/person:levi_signal",
        "when": 2410089026.0,
        "datetime": "2046-05-16T08:10:26",
        "event_id": 369812
      },
      {
        "depth": 170,
        "from": "Agent/person:levi_signal",
        "to": "Agent/person:evelyn_dock",
        "when": 2410089568.0,
        "datetime": "2046-05-16T08:19:28",
        "event_id": 369837
      },
      {
        "depth": 171,
        "from": "Agent/person:evelyn_dock",
        "to": "Agent/person:chloe_ballast",
        "when": 2410096576.0,
        "datetime": "2046-05-16T10:16:16",
        "event_id": 370227
      },
      {
        "depth": 172,
        "from": "Agent/person:chloe_ballast",
        "to": "Agent/person:michael_capstan",
        "when": 2410102478.0,
        "datetime": "2046-05-16T11:54:38",
        "event_id": 370548
      },
      {
        "depth": 173,
        "from": "Agent/person:michael_capstan",
        "to": "Agent/person:michael_capstan",
        "when": 2410109511.0,
        "datetime": "2046-05-16T13:51:51",
        "event_id": 370916
      },
      {
        "depth": 174,
        "from": "Agent/person:michael_capstan",
        "to": "Agent/person:michael_capstan",
        "when": 2410116601.0,
        "datetime": "2046-05-16T15:50:01",
        "event_id": 371331
      },
      {
        "depth": 175,
        "from": "Agent/person:michael_capstan",
        "to": "Agent/person:mia_fender",
        "when": 2410122525.0,
        "datetime": "2046-05-16T17:28:45",
        "event_id": 371557
      },
      {
        "depth": 176,
        "from": "Agent/person:mia_fender",
        "to": "Agent/person:james_stern",
        "when": 2410127325.0,
        "datetime": "2046-05-16T18:48:45",
        "event_id": 371890
      },
      {
        "depth": 177,
        "from": "Agent/person:james_stern",
        "to": "Agent/person:gabriel_sonar",
        "when": 2410131103.0,
        "datetime": "2046-05-16T19:51:43",
        "event_id": 372157
      },
      {
        "depth": 178,
        "from": "Agent/person:gabriel_sonar",
        "to": "Agent/person:daniel_gangway",
        "when": 2410136771.0,
        "datetime": "2046-05-16T21:26:11",
        "event_id": 372473
      },
      {
        "depth": 179,
        "from": "Agent/person:daniel_gangway",
        "to": "Agent/person:zoey_drydock",
        "when": 2410143152.0,
        "datetime": "2046-05-16T23:12:32",
        "event_id": 372821
      },
      {
        "depth": 180,
        "from": "Agent/person:zoey_drydock",
        "to": "Agent/person:mia_fender",
        "when": 2410148072.0,
        "datetime": "2046-05-17T00:34:32",
        "event_id": 373064
      },
      {
        "depth": 181,
        "from": "Agent/person:mia_fender",
        "to": "Agent/person:victoria_rigging",
        "when": 2410149171.0,
        "datetime": "2046-05-17T00:52:51",
        "event_id": 373130
      },
      {
        "depth": 182,
        "from": "Agent/person:victoria_rigging",
        "to": "Agent/person:zoey_drydock",
        "when": 2410152268.0,
        "datetime": "2046-05-17T01:44:28",
        "event_id": 373282
      },
      {
        "depth": 183,
        "from": "Agent/person:zoey_drydock",
        "to": "Agent/person:lily_anchorline",
        "when": 2410157767.0,
        "datetime": "2046-05-17T03:16:07",
        "event_id": 373635
      },
      {
        "depth": 184,
        "from": "Agent/person:lily_anchorline",
        "to": "Agent/person:daniel_gangway",
        "when": 2410164691.0,
        "datetime": "2046-05-17T05:11:31",
        "event_id": 373831
      },
      {
        "depth": 185,
        "from": "Agent/person:daniel_gangway",
        "to": "Agent/person:chloe_ballast",
        "when": 2410168344.0,
        "datetime": "2046-05-17T06:12:24",
        "event_id": 373882
      },
      {
        "depth": 186,
        "from": "Agent/person:chloe_ballast",
        "to": "Agent/person:john_windward",
        "when": 2410168873.0,
        "datetime": "2046-05-17T06:21:13",
        "event_id": 373893
      }
    ]
  }
}